odoo8_addon_purchase_department-8.0.1.0.0-py2.7-nspkg.pth
odoo_addons/purchase_department/__openerp__.py
odoo_addons/purchase_department/__init__.py
odoo_addons/purchase_department/README.rst
odoo_addons/purchase_department/view/purchase_order_line.xml
odoo_addons/purchase_department/view/purchase_order.xml
odoo_addons/purchase_department/model/purchase.py
odoo_addons/purchase_department/model/__init__.py
odoo_addons/purchase_department/tests/__init__.py
odoo_addons/purchase_department/tests/test_propagate_department.py
odoo8_addon_purchase_department-8.0.1.0.0.dist-info/top_level.txt
odoo8_addon_purchase_department-8.0.1.0.0.dist-info/WHEEL
odoo8_addon_purchase_department-8.0.1.0.0.dist-info/RECORD
odoo8_addon_purchase_department-8.0.1.0.0.dist-info/metadata.json
odoo8_addon_purchase_department-8.0.1.0.0.dist-info/DESCRIPTION.rst
odoo8_addon_purchase_department-8.0.1.0.0.dist-info/METADATA
odoo8_addon_purchase_department-8.0.1.0.0.dist-info/namespace_packages.txt
